<annotation>
  <folder/>
  <filename>2020-04-04 11:14:42.528355127.jpg</filename>
  <database/>
  <annotation/>
  <image/>
  <size>
    <height>1080</height>
    <width>1920</width>
    <depth>3</depth>
  </size>
  <segmented/>
  <object>
    <name>red</name>
    <pose/>
    <truncated/>
    <difficult/>
    <bndbox>
      <xmin>998</xmin>
      <ymin>367</ymin>
      <xmax>1018</xmax>
      <ymax>390</ymax>
    </bndbox>
  </object>
  <object>
    <name>green</name>
    <pose/>
    <truncated/>
    <difficult/>
    <bndbox>
      <xmin>1056</xmin>
      <ymin>366</ymin>
      <xmax>1086</xmax>
      <ymax>387</ymax>
    </bndbox>
  </object>
</annotation>
