<annotation>
  <folder/>
  <filename>2020-04-04 11:14:43.536858954.jpg</filename>
  <database/>
  <annotation/>
  <image/>
  <size>
    <height>1080</height>
    <width>1920</width>
    <depth>3</depth>
  </size>
  <segmented/>
  <object>
    <name>wait_on</name>
    <pose/>
    <truncated/>
    <difficult/>
    <bndbox>
      <xmin>1206</xmin>
      <ymin>205</ymin>
      <xmax>1400</xmax>
      <ymax>231</ymax>
    </bndbox>
  </object>
  <object>
    <name>green</name>
    <pose/>
    <truncated/>
    <difficult/>
    <bndbox>
      <xmin>1346</xmin>
      <ymin>245</ymin>
      <xmax>1409</xmax>
      <ymax>283</ymax>
    </bndbox>
  </object>
  <object>
    <name>red</name>
    <pose/>
    <truncated/>
    <difficult/>
    <bndbox>
      <xmin>1200</xmin>
      <ymin>252</ymin>
      <xmax>1265</xmax>
      <ymax>286</ymax>
    </bndbox>
  </object>
</annotation>
