<annotation>
  <folder/>
  <filename>2020-04-04 11:17:08.334789715.jpg</filename>
  <database/>
  <annotation/>
  <image/>
  <size>
    <height>1080</height>
    <width>1920</width>
    <depth>3</depth>
  </size>
  <segmented/>
  <object>
    <name>red</name>
    <pose/>
    <truncated/>
    <difficult/>
    <bndbox>
      <xmin>662</xmin>
      <ymin>420</ymin>
      <xmax>696</xmax>
      <ymax>436</ymax>
    </bndbox>
  </object>
  <object>
    <name>green</name>
    <pose/>
    <truncated/>
    <difficult/>
    <bndbox>
      <xmin>701</xmin>
      <ymin>419</ymin>
      <xmax>739</xmax>
      <ymax>439</ymax>
    </bndbox>
  </object>
</annotation>
